crxcavator/__init__.py
crxcavator/__main__.py
crxcavator/api.py
crxcavatorpy-0.1.3.dist-info/METADATA
crxcavatorpy-0.1.3.dist-info/WHEEL
crxcavatorpy-0.1.3.dist-info/RECORD
