Metadata-Version: 2.1
Name: crxcavatorpy
Version: 0.1.3
Summary: Python module for interacting with the Crxcavator api
Author: Garrett Primm
Author-email: garrett@alabamacloudsecurity.com
Requires-Python: >=3.8.1
Classifier: Programming Language :: Python :: 3
Classifier: Programming Language :: Python :: 3.9
Classifier: Programming Language :: Python :: 3.10
Classifier: Programming Language :: Python :: 3.11
Requires-Dist: argparse (>=1.4.0,<2.0.0)
Requires-Dist: requests (>=2.31.0,<3.0.0)
